ldapper/__init__.py
ldapper/connection.py
ldapper/exceptions.py
ldapper/fields.py
ldapper/ldapnode.py
ldapper/logging.py
ldapper/query.py
ldapper/utils.py
ldapper-1.0.3.dist-info/LICENSE
ldapper-1.0.3.dist-info/METADATA
ldapper-1.0.3.dist-info/WHEEL
ldapper-1.0.3.dist-info/top_level.txt
ldapper-1.0.3.dist-info/RECORD
