Metadata-Version: 2.1
Name: ldapper
Version: 1.0.3
Summary: LDAP ORM for Python
Home-page: https://github.com/UMIACS/ldapper
Author: Liam Monahan
Author-email: liam@liammonahan.com
License: LGPL v2.1
Platform: UNIX/Linux
Classifier: Development Status :: 5 - Production/Stable
Classifier: Intended Audience :: Developers
Classifier: Intended Audience :: System Administrators
Classifier: Operating System :: OS Independent
Classifier: Operating System :: MacOS :: MacOS X
Classifier: Operating System :: Microsoft :: Windows
Classifier: Operating System :: POSIX
Classifier: Programming Language :: Python :: 3
Classifier: Programming Language :: Python :: 3.6
Classifier: Programming Language :: Python :: 3.7
Classifier: Programming Language :: Python :: 3.8
Classifier: Topic :: Database
Classifier: Topic :: Internet
Classifier: Topic :: Software Development :: Libraries :: Python Modules
Classifier: Topic :: System :: Systems Administration :: Authentication/Directory :: LDAP
Requires-Dist: inflection
Requires-Dist: python-ldap (>=2.4.15)
